gtimelog2toggl/__init__.py
gtimelog2toggl/cli.py
gtimelog2toggl/config.py
gtimelog2toggl/config.yml
gtimelog2toggl/core.py
gtimelog2toggl-0.1.dist-info/METADATA
gtimelog2toggl-0.1.dist-info/WHEEL
gtimelog2toggl-0.1.dist-info/entry_points.txt
gtimelog2toggl-0.1.dist-info/top_level.txt
gtimelog2toggl-0.1.dist-info/RECORD
