Metadata-Version: 2.1
Name: gtimelog2toggl
Version: 0.1
Summary: A simple script for importing gtimelog time entries into Toggl Track.
Home-page: https://github.com/jpsnyder/gtimelog2toggl
Author: Jonathan Snyder
Author-email: jonsnyder1@gmail.com
License: MIT
Platform: UNKNOWN
Requires-Dist: appdirs
Requires-Dist: click
Requires-Dist: gtimelog
Requires-Dist: python-box
Requires-Dist: ruamel.yaml
Requires-Dist: TogglPy
